mujoco_toolbox/__init__.py
mujoco_toolbox/assets.py
mujoco_toolbox/builder.py
mujoco_toolbox/controllers.py
mujoco_toolbox/loader.py
mujoco_toolbox/sim.py
mujoco_toolbox/templates/glovebox.xml
mujoco_toolbox/templates/world.xml
mujoco_toolbox/utils.py
mujoco_toolbox/warnings.py
mujoco_toolbox-0.6.3.dist-info/LICENSE
mujoco_toolbox-0.6.3.dist-info/METADATA
mujoco_toolbox-0.6.3.dist-info/WHEEL
mujoco_toolbox-0.6.3.dist-info/RECORD
