Metadata-Version: 2.3
Name: mujoco-toolbox
Version: 0.6.3
Summary: A Modern Simulation Wrapper for Google DeepMind's MuJoCo
License: MIT License
Keywords: MuJoCo,mujoco,robotics,simulation,toolbox,wrapper
Author: MGross21
Author-email: MGross21@example.com
Requires-Python: >=3.9,<4.0
Classifier: Development Status :: 4 - Beta
Classifier: Intended Audience :: Developers
Classifier: License :: OSI Approved :: MIT License
Classifier: Programming Language :: Python :: 3.9
Classifier: Programming Language :: Python :: 3.10
Classifier: Programming Language :: Python :: 3.11
Classifier: Programming Language :: Python :: 3.12
Classifier: Programming Language :: Python :: 3.13
Classifier: Operating System :: OS Independent
Provides-Extra: gym
Requires-Dist: colorama
Requires-Dist: defusedxml (>=0.7.1,<0.8.0)
Requires-Dist: ffmpeg
Requires-Dist: gym ; extra == "gym"
Requires-Dist: imageio[ffmpeg]
Requires-Dist: ipywidgets
Requires-Dist: jinja2
Requires-Dist: matplotlib
Requires-Dist: mujoco
Requires-Dist: numpy
Requires-Dist: pyyaml
Requires-Dist: rich
Requires-Dist: scipy
Requires-Dist: screeninfo
Requires-Dist: tqdm
Requires-Dist: trimesh
Project-URL: Bug Tracker, https://github.com/MGross21/mujoco-toolbox/issues
Project-URL: Documentation, https://mgross21.github.io/mujoco-toolbox/
Project-URL: Homepage, https://github.com/MGross21/mujoco-toolbox
Project-URL: Repository, https://github.com/MGross21/mujoco-toolbox
Project-URL: changelog, https://github.com/MGross21/mujoco-toolbox/blob/main/CHANGELOG.md
